custom_package/__init__.py
custom_package/db_binding.py
custom_package/db_config.py
custom_package/db_handler.py
custom_package/managers/customers_managers.py
custom_package/models/__init__.py
custom_package/models/customers.py
custom_package-0.1.2.dist-info/WHEEL
custom_package-0.1.2.dist-info/METADATA
custom_package-0.1.2.dist-info/RECORD
