Metadata-Version: 2.1
Name: custom-package
Version: 0.1.2
Summary: Demo Custom Package
Author: MeetParikh01
Author-email: meet.parikh@tntra.io
Requires-Python: >=3.8,<4.0
Classifier: Programming Language :: Python :: 3
Classifier: Programming Language :: Python :: 3.10
Classifier: Programming Language :: Python :: 3.8
Classifier: Programming Language :: Python :: 3.9
Requires-Dist: SQLAlchemy (==1.4.29)
Requires-Dist: SQLAlchemy-Utils (==0.38.2)
Requires-Dist: alembic (==1.7.5)
Requires-Dist: psycopg2-binary (==2.9.3)
